drcom/__init__.py
drcom/__main__.py
drcom/configs/__init__.py
drcom/configs/settings.py
drcom/gui/__init__.py
drcom/gui/window.py
drcom/main/__init__.py
drcom/main/client.py
drcom/main/excepts.py
drcom/main/logger.py
drcom/main/tool.py
drcom/main/utils.py
MagicDrCOM-1.2.0.dist-info/LICENSE
MagicDrCOM-1.2.0.dist-info/METADATA
MagicDrCOM-1.2.0.dist-info/WHEEL
MagicDrCOM-1.2.0.dist-info/top_level.txt
MagicDrCOM-1.2.0.dist-info/RECORD
