Metadata-Version: 2.1
Name: MagicDrCOM
Version: 1.2.0
Summary: 3rd DrCOM client
Home-page: https://github.com/ryuchen/MagicDrCOM
Author: ryuchen
Author-email: chenhaom1993@hotmail.com
Maintainer: Ryuchen
Maintainer-email: chenhaom1993@hotmail.com
License: GNU General Public License v3 (GPLv3)
Platform: all
Classifier: Development Status :: 3 - Alpha
Classifier: Natural Language :: Chinese (Simplified)
Classifier: Operating System :: Microsoft :: Windows :: Windows 10
Classifier: Operating System :: MacOS
Classifier: Operating System :: POSIX :: Linux
Classifier: Environment :: Console
Classifier: Environment :: MacOS X
Classifier: Environment :: Win32 (MS Windows)
Classifier: Intended Audience :: Developers
Classifier: License :: OSI Approved :: GNU General Public License v3 (GPLv3)
Classifier: Programming Language :: Python :: 3
Requires-Python: >=3.6
Requires-Dist: PySide2
